howl/__init__.py
howl/context.py
howl/logger.py
howl/registered.py
howl/settings.py
howl/client/__init__.py
howl/client/howl_client.py
howl/data/__init__.py
howl/data/dataloader.py
howl/data/tokenize.py
howl/data/dataset/__init__.py
howl/data/dataset/base.py
howl/data/dataset/dataset.py
howl/data/dataset/phone.py
howl/data/dataset/serialize.py
howl/data/transform/__init__.py
howl/data/transform/augment.py
howl/data/transform/base.py
howl/data/transform/meyda.py
howl/model/__init__.py
howl/model/base.py
howl/model/cnn.py
howl/model/inference.py
howl/model/metric.py
howl/model/rnn.py
howl/model/workspace.py
howl/utils/__init__.py
howl/utils/audio.py
howl/utils/dataclass.py
howl/utils/hash.py
howl/utils/random.py
howl/utils/transcribe.py
howl-0.1.2.dist-info/LICENSE
howl-0.1.2.dist-info/METADATA
howl-0.1.2.dist-info/WHEEL
howl-0.1.2.dist-info/top_level.txt
howl-0.1.2.dist-info/RECORD
