Metadata-Version: 2.1
Name: howl
Version: 0.1.2
Summary: A wake word detection toolkit
Home-page: https://github.com/castorini/howl
Author: Anserini Gaggle
Author-email: anserini.gaggle@gmail.com
License: UNKNOWN
Platform: UNKNOWN
Classifier: License :: OSI Approved :: Mozilla Public License 2.0 (MPL 2.0)
Classifier: Operating System :: OS Independent
Classifier: Programming Language :: Python :: 3
Classifier: Programming Language :: Python :: 3.6
Classifier: Programming Language :: Python :: 3.7
Classifier: Programming Language :: Python :: 3.8
Classifier: Topic :: Multimedia :: Sound/Audio
Classifier: Topic :: Multimedia :: Sound/Audio :: Speech
Requires-Python: >=3.6
Requires-Dist: coloredlogs
Requires-Dist: librosa (>=0.8.0)
Requires-Dist: numpy (>=1.18.3)
Requires-Dist: pandas (>=1.0.3)
Requires-Dist: pocketsphinx
Requires-Dist: pyaudio
Requires-Dist: pydantic (>=1.7.3)
Requires-Dist: soundfile (==0.10.3.post1)
Requires-Dist: tensorboard
Requires-Dist: tqdm
Requires-Dist: torch (>=1.5.0)
Requires-Dist: torchaudio (>=0.5.0)
Requires-Dist: torchvision (>=0.6.0)
Requires-Dist: dataclasses ; python_version < "3.7"
